Metadata-Version: 1.1
Name: python-alipay-sdk
Version: 2.1.1
Summary: Python SDK for AliPay, RSA is the only sign method we support
Home-page: https://github.com/fzlee/alipay
Author: fzlee
Author-email: fzleee@gmail.com
License: BSD
Keywords: python sdk alipay
Platform: UNKNOWN
Classifier: Development Status :: 3 - Alpha
Classifier: Topic :: Utilities
Classifier: License :: OSI Approved :: BSD License
Classifier: Programming Language :: Python :: 3.4
Classifier: Programming Language :: Python :: 3.5
Classifier: Programming Language :: Python :: 3.6
Classifier: Programming Language :: Python :: 3.7
Classifier: Programming Language :: Python :: 3.8
